jnp/__init__.py
jnp/bugfixes.py
jnp/common.py
jnp/config.py
jnp/css.py
jnp/file.py
jnp/main.py
jnp/manager.py
jnp/notebook.py
jnp/text.py
jnp/version.py
jnp/resources/index.css
jnp/resources/index.html
jnp/resources/main.css
jnp/resources/reveal.css
jnp/resources/sizes.css
jnp-2024.5.dist-info/METADATA
jnp-2024.5.dist-info/WHEEL
jnp-2024.5.dist-info/entry_points.txt
jnp-2024.5.dist-info/licenses/LICENSE.txt
jnp-2024.5.dist-info/RECORD
