Metadata-Version: 2.3
Name: jnp
Version: 2024.5
Summary: Export Jupyter notebook presentations with custom CSS.
Project-URL: Homepage, https://gitlab.inria.fr/jrye/jnp
Project-URL: Source, https://gitlab.inria.fr/jrye/jnp.git
Project-URL: Documentation, https://jrye.gitlabpages.inria.fr/jnp
Project-URL: Issues, https://gitlab.inria.fr/jrye/jnp/-/issues
Author-email: Jan-Michael Rye <jan-michael.rye@inria.fr>
License: MIT License
License-File: LICENSE.txt
Classifier: License :: OSI Approved :: MIT License
Classifier: Operating System :: OS Independent
Classifier: Programming Language :: Python :: 3
Requires-Python: >=3.6
Requires-Dist: ipython
Requires-Dist: jupyterlab-pygments
Requires-Dist: nbconvert
Requires-Dist: pygments
Requires-Dist: pyyaml
